md_format_hook/__init__.py
md_format_hook/md_format.py
md_format_hook-0.0.5.dist-info/LICENSE
md_format_hook-0.0.5.dist-info/METADATA
md_format_hook-0.0.5.dist-info/WHEEL
md_format_hook-0.0.5.dist-info/entry_points.txt
md_format_hook-0.0.5.dist-info/top_level.txt
md_format_hook-0.0.5.dist-info/RECORD
