Metadata-Version: 2.1
Name: md-format-hook
Version: 0.0.5
Summary: Adds reasonable spaces between Chinese and English and corrects the case of special nouns.
Home-page: https://github.com/PKUcoldkeyboard/md-format
Author: cuterwrite
Author-email: 158505862@qq.com
License: MIT
Classifier: License :: OSI Approved :: MIT License
Classifier: Programming Language :: Python :: 3
Classifier: Programming Language :: Python :: 3 :: Only
Requires-Python: >=3.8
License-File: LICENSE
Requires-Dist: pangu (>=4.0.0)
